spectrosense/__init__.py
spectrosense/ai_integration.py
spectrosense/analyzer.py
spectrosense/config.py
spectrosense/image_analysis.py
spectrosense/processor.py
spectrosense/visualizer.py
spectrosense-0.3.0.dist-info/LICENCE
spectrosense-0.3.0.dist-info/METADATA
spectrosense-0.3.0.dist-info/WHEEL
spectrosense-0.3.0.dist-info/top_level.txt
spectrosense-0.3.0.dist-info/RECORD
