Metadata-Version: 2.2
Name: spectrosense
Version: 0.3.0
Summary: AI-powered RF signal analysis and classification
Home-page: https://github.com/oldhero5/spectrosense
Author: Marty H
Author-email: Marty Harris <adeptbison@proton.me>
Requires-Python: >=3.8
License-File: LICENCE
Requires-Dist: numpy
Requires-Dist: scipy
Requires-Dist: matplotlib
Requires-Dist: anthropic
Requires-Dist: pillow
Dynamic: author
Dynamic: home-page
Dynamic: requires-python
